odoo8_addon_web_search_with_and-8.0.1.0.0-py2.7-nspkg.pth
odoo_addons/web_search_with_and/__openerp__.py
odoo_addons/web_search_with_and/__init__.py
odoo_addons/web_search_with_and/README.rst
odoo_addons/web_search_with_and/data/data.xml
odoo_addons/web_search_with_and/static/src/js/search.js
odoo8_addon_web_search_with_and-8.0.1.0.0.dist-info/top_level.txt
odoo8_addon_web_search_with_and-8.0.1.0.0.dist-info/WHEEL
odoo8_addon_web_search_with_and-8.0.1.0.0.dist-info/RECORD
odoo8_addon_web_search_with_and-8.0.1.0.0.dist-info/metadata.json
odoo8_addon_web_search_with_and-8.0.1.0.0.dist-info/DESCRIPTION.rst
odoo8_addon_web_search_with_and-8.0.1.0.0.dist-info/METADATA
odoo8_addon_web_search_with_and-8.0.1.0.0.dist-info/namespace_packages.txt
